better_nested_serializer/__init__.py
better_nested_serializer/helpers.py
better_nested_serializer/exceptions/__init__.py
better_nested_serializer/exceptions/serializers.py
better_nested_serializer/serializers/__init__.py
better_nested_serializer/serializers/list_serializer.py
better_nested_serializer/serializers/model_serializer.py
better_nested_serializer-0.1.5.dist-info/METADATA
better_nested_serializer-0.1.5.dist-info/WHEEL
better_nested_serializer-0.1.5.dist-info/top_level.txt
better_nested_serializer-0.1.5.dist-info/RECORD
