Metadata-Version: 2.4
Name: better-nested-serializer
Version: 0.1.5
Summary: A better DRF [Django REST Framework] serializer that normalizes nested objects into separate lists for improved performance
Author-email: Rudra <rudra.ofive@gmail.com>
License: MIT
Project-URL: Homepage, https://github.com/sree93/better_drf_nested_serializer
Project-URL: Repository, https://github.com/sree93/better_drf_nested_serializer
Project-URL: Issues, https://github.com/sree93/better_drf_nested_serializer/issues
Keywords: django,rest-framework,serializer,performance
Classifier: Development Status :: 3 - Alpha
Classifier: Intended Audience :: Developers
Classifier: License :: OSI Approved :: MIT License
Classifier: Programming Language :: Python :: 3
Classifier: Programming Language :: Python :: 3.11
Classifier: Programming Language :: Python :: 3.12
Classifier: Framework :: Django
Classifier: Topic :: Software Development :: Libraries :: Python Modules
Requires-Python: >=3.11
Requires-Dist: deepmerge>=2.0
Requires-Dist: djangorestframework>=3
